molecule_gce/__init__.py
molecule_gce/driver.py
molecule_gce/cookiecutter/cookiecutter.json
molecule_gce/cookiecutter/{{cookiecutter.molecule_directory}}/{{cookiecutter.scenario_name}}/converge.yml
molecule_gce/playbooks/create.yml
molecule_gce/playbooks/destroy.yml
molecule_gce/playbooks/files/windows_auth.py
molecule_gce/playbooks/handlers/main.yml
molecule_gce/playbooks/tasks/create_linux_instance.yml
molecule_gce/playbooks/tasks/create_windows_instance.yml
molecule_gce/test/__init__.py
molecule_gce/test/test_driver.py
molecule_gce/test/functional/.ansible-lint
molecule_gce/test/functional/__init__.py
molecule_gce/test/functional/conftest.py
molecule_gce/test/functional/test_func.py
molecule_gce-1.0.0.dist-info/LICENSE
molecule_gce-1.0.0.dist-info/METADATA
molecule_gce-1.0.0.dist-info/WHEEL
molecule_gce-1.0.0.dist-info/entry_points.txt
molecule_gce-1.0.0.dist-info/top_level.txt
molecule_gce-1.0.0.dist-info/RECORD
