Metadata-Version: 2.1
Name: molecule-gce
Version: 1.0.0
Summary: Molecule GCE Plugin :: run molecule tests on Google Cloud Engine
Home-page: https://github.com/ansible-community/molecule-gce
Author: Ansible by Red Hat
Author-email: info@ansible.com
Maintainer: Ansible by Red Hat
Maintainer-email: info@ansible.com
License: MIT
Project-URL: Bug Tracker, https://github.com/ansible-community/molecule-gce/issues
Project-URL: Release Management, https://github.com/ansible-community/molecule-gce/releases
Project-URL: CI, https://github.com/ansible-community/molecule-gce/actions
Project-URL: Discussions, https://github.com/ansible-community/molecule/discussions
Project-URL: Source Code, https://github.com/ansible-community/molecule-gce
Keywords: ansible,roles,testing,molecule,plugin,gce,google
Classifier: Development Status :: 4 - Beta
Classifier: Environment :: Console
Classifier: Intended Audience :: Developers
Classifier: Intended Audience :: Information Technology
Classifier: Intended Audience :: System Administrators
Classifier: License :: OSI Approved :: MIT License
Classifier: Natural Language :: English
Classifier: Operating System :: OS Independent
Classifier: Programming Language :: Python :: 3
Classifier: Programming Language :: Python :: 3.8
Classifier: Programming Language :: Python :: 3.9
Classifier: Programming Language :: Python :: 3.10
Classifier: Topic :: System :: Systems Administration
Classifier: Topic :: Utilities
Requires-Python: >=3.8
License-File: LICENSE
Requires-Dist: molecule (>=3.4.0)
Requires-Dist: pyyaml (>=5.1)
Requires-Dist: pywinrm (>=0.3.0)
Requires-Dist: google-auth (>=1.34.0)
Requires-Dist: google-api-python-client (>=2.15.0)
Requires-Dist: jinja2-ansible-filters (>=1.3.0)
Requires-Dist: pycryptodome (>=3.10.1)
Provides-Extra: test
Requires-Dist: molecule[test] ; extra == 'test'
